wfmess/__init__.py
wfmess/chopper.py
wfmess/frames_analytical.py
wfmess/frames_peakfinding.py
wfmess/stitch.py
wfmess/stitch_events.py
wfmess/stitch_files.py
wfmess/stitch_histogram.py
wfmess/tools.py
wfmess/v20.py
wfmess/wfmess.py
wfmess-0.0.3.dist-info/LICENSE
wfmess-0.0.3.dist-info/METADATA
wfmess-0.0.3.dist-info/WHEEL
wfmess-0.0.3.dist-info/top_level.txt
wfmess-0.0.3.dist-info/RECORD
