Metadata-Version: 2.1
Name: wfmess
Version: 0.0.3
Summary: Wave-Frame Multiplication data reduction for ESS
Home-page: https://github.com/nvaytet/wfmess
Author: Neil Vaytet
Author-email: neil.vaytet@esss.se
License: UNKNOWN
Platform: UNKNOWN
Classifier: Programming Language :: Python :: 2
Classifier: Programming Language :: Python :: 3
Classifier: License :: OSI Approved :: GNU General Public License v3 or later (GPLv3+)
Classifier: Operating System :: OS Independent
Requires-Dist: matplotlib
Requires-Dist: numpy
Requires-Dist: h5py
Requires-Dist: scipy
